{
  "0": {
    "73711": 55272
  },
  "1": {
    "33247": 35519,
    "35263": 31099
  },
  "2": {
    "13490": 2002
  },
  "3": {
    "89779": 91278
  },
  "4": {
    "45176": 39166
  },
  "5": {
    "8804": 6546
  },
  "6": {
    "21913": 23181
  },
  "7": {
    "59419": 76322
  },
  "8": {
    "89681": 90620
  },
  "9": {
    "38304": 38763,
    "61522": 60569
  },
  "10": {
    "5283": 4836
  },
  "11": {
    "66431": 50927
  },
  "12": {
    "67100": 67013
  },
  "13": {
    "66969": 68345
  }
}